firestore_rest/__init__.py
firestore_rest/credentials.py
firestore_rest/firestore.py
firestore_rest/firestore_utils.py
firestore_rest-0.1.dist-info/LICENSE
firestore_rest-0.1.dist-info/METADATA
firestore_rest-0.1.dist-info/WHEEL
firestore_rest-0.1.dist-info/top_level.txt
firestore_rest-0.1.dist-info/RECORD
