Metadata-Version: 2.1
Name: firestore-rest
Version: 0.1
Summary: A Firestore REST api utility package
Home-page: https://github.com/evan-richard/firestore_rest
Author: Evan Richard
Author-email: evan.richard.umd@gmail.com
License: UNKNOWN
Platform: UNKNOWN
Classifier: Programming Language :: Python :: 2.6
Classifier: License :: OSI Approved :: MIT License
Classifier: Operating System :: OS Independent
